xcomfortshc/__init__.py
xcomfortshc-0.1.dist-info/LICENSE
xcomfortshc-0.1.dist-info/METADATA
xcomfortshc-0.1.dist-info/WHEEL
xcomfortshc-0.1.dist-info/top_level.txt
xcomfortshc-0.1.dist-info/RECORD
