Metadata-Version: 2.1
Name: xcomfortshc
Version: 0.1
Summary: Eaton xComfort Smart Home Controller communinication library.
Home-page: https://github.com/plamish/xcomfort-shc
Author: plamish
License: MIT
Platform: UNKNOWN
Classifier: Programming Language :: Python :: 3
Classifier: License :: OSI Approved :: MIT License
Classifier: Operating System :: OS Independent
Requires-Python: >=3.6.0
License-File: LICENSE
Requires-Dist: aiohttp (>=3.5.4)
